tubeulator-0.1.3.dist-info/METADATA
tubeulator-0.1.3.dist-info/WHEEL
tubeulator-0.1.3.dist-info/entry_points.txt
tubeulator-0.1.3.dist-info/licenses/LICENSE.txt
tubeulator/__init__.py
tubeulator/api/__init__.py
tubeulator/api/endpoint/__init__.py
tubeulator/api/endpoint/names.py
tubeulator/api/endpoint/routes/__init__.py
tubeulator/api/endpoint/routes/accident.py
tubeulator/api/endpoint/routes/air.py
tubeulator/api/endpoint/routes/bike.py
tubeulator/api/endpoint/routes/crowding.py
tubeulator/api/endpoint/routes/disruption_lifts.py
tubeulator/api/endpoint/routes/journey.py
tubeulator/api/endpoint/routes/line.py
tubeulator/api/endpoint/routes/mode.py
tubeulator/api/endpoint/routes/occupancy.py
tubeulator/api/endpoint/routes/place.py
tubeulator/api/endpoint/routes/road.py
tubeulator/api/endpoint/routes/search.py
tubeulator/api/endpoint/routes/stop.py
tubeulator/api/endpoint/routes/types.py
tubeulator/api/endpoint/routes/vehicle.py
tubeulator/api/interface.py
tubeulator/api/request.py
tubeulator/cli.py
tubeulator/codegen/__init__.py
tubeulator/codegen/gen/__init__.py
tubeulator/codegen/gen/dto.py
tubeulator/codegen/gen/emit.py
tubeulator/codegen/gen/helpers.py
tubeulator/codegen/gen/jsonschema.py
tubeulator/codegen/gen/resolution.py
tubeulator/codegen/load_test.py
tubeulator/codegen/populate.py
tubeulator/data/db/credentials.json
tubeulator/data/openapi/AccidentStats/AccidentStats.json
tubeulator/data/openapi/AccidentStats/schemas/accidentdetail.json
tubeulator/data/openapi/AccidentStats/schemas/all.json
tubeulator/data/openapi/AccidentStats/schemas/casualty.json
tubeulator/data/openapi/AccidentStats/schemas/tfl-api-presentation-entities-accidentstats-accidentdetailarray-1.json
tubeulator/data/openapi/AccidentStats/schemas/tfl-api-presentation-entities-accidentstats-accidentdetailarray-2.json
tubeulator/data/openapi/AccidentStats/schemas/tfl-api-presentation-entities-accidentstats-accidentdetailarray-3.json
tubeulator/data/openapi/AccidentStats/schemas/tfl-api-presentation-entities-accidentstats-accidentdetailarray.json
tubeulator/data/openapi/AccidentStats/schemas/vehicle.json
tubeulator-0.1.3.dist-info/RECORD
