Metadata-Version: 2.1
Name: tubeulator
Version: 0.1.3
Summary: TfL open data interface library.
Author-Email: Louis Maddox <louismmx@gmail.com>
License: MIT
Classifier: Intended Audience :: Developers
Classifier: Programming Language :: Python :: 3.10
Classifier: Programming Language :: Python :: 3.11
Classifier: Programming Language :: Python :: 3.12
Classifier: Programming Language :: Python :: 3.13
Project-URL: Homepage, https://github.com/lmmx/tubeulator
Project-URL: Repository, https://github.com/lmmx/tubeulator.git
Requires-Python: <3.14,>=3.10
Requires-Dist: defopt
Requires-Dist: httpx
Requires-Dist: jsonschema
Requires-Dist: orjson
Requires-Dist: patito>=0.6.1
Requires-Dist: polars>=0.20.17
Requires-Dist: pydantic>=2.6.4
Requires-Dist: tinydb>=4.8.2
Requires-Dist: urllib3<2
Provides-Extra: dev
Requires-Dist: pre-commit>=4.1.0; extra == "dev"
Provides-Extra: folium
Requires-Dist: folium>=0.16.0; extra == "folium"
Provides-Extra: polars-lts-cpu
Requires-Dist: patito>=0.6.1; extra == "polars-lts-cpu"
Requires-Dist: polars-lts-cpu>=0.20.17; extra == "polars-lts-cpu"
